tandem/__init__.py
tandem/sprt_tandem_main.py
tandem/config/__init__.py
tandem/config/config_definition.py
tandem/data/__init__.py
tandem/data/train_10000/__init__.py
tandem/data/train_10000/data.mdb
tandem/data/train_10000/lock.mdb
tandem/data/val_100/__init__.py
tandem/data/val_100/data.mdb
tandem/data/val_100/lock.mdb
tandem/models/__init__.py
tandem/models/losses.py
tandem/models/optimizers.py
tandem/models/temporal_integrators.py
tandem/utils/__init__.py
tandem/utils/checkpoint.py
tandem/utils/data_processing.py
tandem/utils/hyperparameter_tuning.py
tandem/utils/logging.py
tandem/utils/misc.py
tandem/utils/performance_metrics.py
tandem/utils/training.py
SPRT_TANDEM-0.1.11.dist-info/LICENSE
SPRT_TANDEM-0.1.11.dist-info/METADATA
SPRT_TANDEM-0.1.11.dist-info/WHEEL
SPRT_TANDEM-0.1.11.dist-info/top_level.txt
SPRT_TANDEM-0.1.11.dist-info/RECORD
